LICENSE
MANIFEST.in
README.txt
setup.py
atomisator/__init__.py
atomisator.readers.egg-info/PKG-INFO
atomisator.readers.egg-info/SOURCES.txt
atomisator.readers.egg-info/dependency_links.txt
atomisator.readers.egg-info/entry_points.txt
atomisator.readers.egg-info/namespace_packages.txt
atomisator.readers.egg-info/not-zip-safe
atomisator.readers.egg-info/requires.txt
atomisator.readers.egg-info/top_level.txt
atomisator/readers/__init__.py
atomisator/readers/folder.py
atomisator/readers/html.py
atomisator/readers/twitter.py
atomisator/readers/docs/README.txt
atomisator/readers/tests/__init__.py
atomisator/readers/tests/test_plugins.py
atomisator/readers/tests/data/stuff.txt
atomisator/readers/tests/data/sub/other.txt